andrewscurves
